pypcreate/__init__.py
pypcreate/create.py
pypcreate/create_func.py
pypcreate/example.yaml
pypcreate/utils.py
pysetup_template/__init__.py
pysetup_template/setup.py
pypcreate-0.2.7.dist-info/LICENSE
pypcreate-0.2.7.dist-info/METADATA
pypcreate-0.2.7.dist-info/WHEEL
pypcreate-0.2.7.dist-info/entry_points.txt
pypcreate-0.2.7.dist-info/top_level.txt
pypcreate-0.2.7.dist-info/RECORD
