Metadata-Version: 2.1
Name: pypcreate
Version: 0.2.7
Summary: Python Package creation tool
Home-page: https://github.com/zhz03/PyPCreate
Author: Zhaoliang Zheng
Author-email: zhz03@g.ucla.edu
License: GNU GENERAL PUBLIC LICENSE V3
Classifier: Topic :: Software Development :: Libraries :: Python Modules
Classifier: Programming Language :: Python
Classifier: Programming Language :: Python :: 3.7
License-File: LICENSE
Requires-Dist: argparse
Requires-Dist: pyyaml
Requires-Dist: requests
